[
     {
  "titulo": "Jugador Destacado en Atenas.",
  "descripcion": " En el debut de Atenas en la liga, estos son sus números",
  "contenido": "",
  "imagen": "figura.png"
  
},
      
      {
  "titulo": "Horario del partido  ",
  "descripcion": " Se conocio el horario del partido del viernes vs a San Martin",
  "contenido": "",
  "imagen": "partido111.png"
  
},
    {
  "titulo": "Atenas  - Plantel Completo ",
  "descripcion": "El debut de Atenas en la temporada de la Liga Nacional de Básquet.",
  "contenido": " Con la llegada de Sanders y Loving, Atenas ya cuenta con plantel completo : Fotos Prensa Atenas | Ignacio Lingua.",
  "imagen": "completo2.jpg"
  
}
  
 
]








































